apispec/__init__.py
apispec/core.py
apispec/exceptions.py
apispec/plugin.py
apispec/py.typed
apispec/utils.py
apispec/yaml_utils.py
apispec/ext/__init__.py
apispec/ext/marshmallow/__init__.py
apispec/ext/marshmallow/common.py
apispec/ext/marshmallow/field_converter.py
apispec/ext/marshmallow/openapi.py
apispec/ext/marshmallow/schema_resolver.py
bitfount_apispec-6.3.0.dist-info/LICENSE
bitfount_apispec-6.3.0.dist-info/METADATA
bitfount_apispec-6.3.0.dist-info/WHEEL
bitfount_apispec-6.3.0.dist-info/top_level.txt
bitfount_apispec-6.3.0.dist-info/RECORD
