Metadata-Version: 2.1
Name: bitfount-apispec
Version: 6.3.0
Summary: A pluggable API specification generator. Currently supports the OpenAPI Specification (f.k.a. the Swagger specification).
Home-page: https://github.com/marshmallow-code/apispec
Author: Steven Loria
Author-email: sloria1@gmail.com
License: MIT
Project-URL: Funding, https://opencollective.com/marshmallow
Project-URL: Issues, https://github.com/marshmallow-code/apispec/issues
Project-URL: Tidelift, https://tidelift.com/subscription/pkg/pypi-apispec?utm_source=pypi-apispec&utm_medium=pypi
Keywords: apispec swagger openapi specification oas documentation spec rest api
Classifier: License :: OSI Approved :: MIT License
Classifier: Programming Language :: Python :: 3
Classifier: Programming Language :: Python :: 3.7
Classifier: Programming Language :: Python :: 3.8
Classifier: Programming Language :: Python :: 3.9
Classifier: Programming Language :: Python :: 3.10
Classifier: Programming Language :: Python :: 3.11
Classifier: Programming Language :: Python :: 3 :: Only
Requires-Python: >=3.7
License-File: LICENSE
Requires-Dist: packaging (>=21.3)
Provides-Extra: dev
Requires-Dist: PyYAML (>=3.10) ; extra == 'dev'
Requires-Dist: prance[osv] (>=0.11) ; extra == 'dev'
Requires-Dist: openapi-spec-validator (<0.5) ; extra == 'dev'
Requires-Dist: marshmallow (>=3.13.0) ; extra == 'dev'
Requires-Dist: pytest ; extra == 'dev'
Requires-Dist: flake8 (==5.0.4) ; extra == 'dev'
Requires-Dist: flake8-bugbear (==22.9.23) ; extra == 'dev'
Requires-Dist: pre-commit (~=2.4) ; extra == 'dev'
Requires-Dist: mypy (==0.982) ; extra == 'dev'
Requires-Dist: types-PyYAML ; extra == 'dev'
Requires-Dist: tox ; extra == 'dev'
Provides-Extra: docs
Requires-Dist: marshmallow (>=3.13.0) ; extra == 'docs'
Requires-Dist: pyyaml (==6.0) ; extra == 'docs'
Requires-Dist: sphinx (==5.2.3) ; extra == 'docs'
Requires-Dist: sphinx-issues (==3.0.1) ; extra == 'docs'
Requires-Dist: sphinx-rtd-theme (==1.0.0) ; extra == 'docs'
Provides-Extra: lint
Requires-Dist: flake8 (==5.0.4) ; extra == 'lint'
Requires-Dist: flake8-bugbear (==22.9.23) ; extra == 'lint'
Requires-Dist: pre-commit (~=2.4) ; extra == 'lint'
Requires-Dist: mypy (==0.982) ; extra == 'lint'
Requires-Dist: types-PyYAML ; extra == 'lint'
Provides-Extra: marshmallow
Requires-Dist: marshmallow (>=3.18.0) ; extra == 'marshmallow'
Provides-Extra: tests
Requires-Dist: PyYAML (>=3.10) ; extra == 'tests'
Requires-Dist: prance[osv] (>=0.11) ; extra == 'tests'
Requires-Dist: openapi-spec-validator (<0.5) ; extra == 'tests'
Requires-Dist: marshmallow (>=3.13.0) ; extra == 'tests'
Requires-Dist: pytest ; extra == 'tests'
Provides-Extra: validation
Requires-Dist: prance[osv] (>=0.11) ; extra == 'validation'
Requires-Dist: openapi-spec-validator (<0.5) ; extra == 'validation'
Provides-Extra: yaml
Requires-Dist: PyYAML (>=3.10) ; extra == 'yaml'
